LICENSE
oc_chess_club/__init__.py
oc_chess_club/__main__.py
oc_chess_club/config.yaml
oc_chess_club/controller/config_loader.py
oc_chess_club/controller/database_handler.py
oc_chess_club/controller/database_helper.py
oc_chess_club/controller/report_handler.py
oc_chess_club/controller/tournament_generator.py
oc_chess_club/controller/tournament_handler.py
oc_chess_club/models/database.py
oc_chess_club/models/match.py
oc_chess_club/models/player.py
oc_chess_club/models/round.py
oc_chess_club/models/tournament.py
oc_chess_club/views/game.py
oc_chess_club/views/helper.py
oc_chess_club/views/main_menu.py
oc_chess_club/views/player_views.py
oc_chess_club/views/report_views.py
oc_chess_club/views/tournament_views.py
oc_chess_club/views/typer_app.py
oc_chess_club-1.0.1.dist-info/LICENSE
oc_chess_club-1.0.1.dist-info/WHEEL
oc_chess_club-1.0.1.dist-info/METADATA
oc_chess_club-1.0.1.dist-info/RECORD
