Metadata-Version: 2.1
Name: oc-chess-club
Version: 1.0.1
Summary: CLI to manage tournaments and players for a chess club
Home-page: https://github.com/PabloLec/oc_chess_club
License: MIT
Keywords: cli,chess,typer
Author: PabloLec
Author-email: pablo.lecolinet@gmail.com
Requires-Python: >=3.9,<4.0
Classifier: Environment :: Console
Classifier: Intended Audience :: End Users/Desktop
Classifier: License :: OSI Approved :: MIT License
Classifier: Operating System :: OS Independent
Classifier: Programming Language :: Python :: 3
Classifier: Programming Language :: Python :: 3.9
Classifier: Topic :: Games/Entertainment :: Board Games
Requires-Dist: PyYAML (>=5.4.1,<6.0.0)
Requires-Dist: colorama (>=0.4.4,<0.5.0)
Requires-Dist: shellingham (>=1.4.0,<2.0.0)
Requires-Dist: tinydb (>=4.4.0,<5.0.0)
Requires-Dist: typer (>=0.3.2,<0.4.0)
Project-URL: Documentation, https://pablolec.github.io/oc_chess_club
Project-URL: Repository, https://github.com/PabloLec/oc_chess_club
